olivia/__init__.py
olivia/olivia.py
olivia-0.3.1.dist-info/WHEEL
olivia-0.3.1.dist-info/METADATA
olivia-0.3.1.dist-info/RECORD
