Metadata-Version: 2.1
Name: olivia
Version: 0.3.1
Summary: Assistente para facilitar requisições HTTP
Author: matheus
Author-email: matheus.mmn@hotmail.com
Requires-Python: >=3.10,<4.0
Classifier: Programming Language :: Python :: 3
Classifier: Programming Language :: Python :: 3.10
Requires-Dist: requests (>=2.28.1,<3.0.0)
